Pweave-0.30.3.dist-info/DESCRIPTION.rst
Pweave-0.30.3.dist-info/METADATA
Pweave-0.30.3.dist-info/RECORD
Pweave-0.30.3.dist-info/WHEEL
Pweave-0.30.3.dist-info/entry_points.txt
Pweave-0.30.3.dist-info/metadata.json
Pweave-0.30.3.dist-info/top_level.txt
pweave/__init__.py
pweave/config.py
pweave/mimetypes.py
pweave/pweb.py
pweave/readers.py
pweave/scripts.py
pweave/bokeh/__init__.py
pweave/formatters/__init__.py
pweave/formatters/base.py
pweave/formatters/jupyter_notebook.py
pweave/formatters/markdown.py
pweave/formatters/markdownmath.py
pweave/formatters/publish.py
pweave/formatters/rst.py
pweave/formatters/templates.py
pweave/formatters/tex.py
pweave/processors/__init__.py
pweave/processors/base.py
pweave/processors/jupyter.py
pweave/processors/subsnippets.py
pweave/themes/__init__.py
pweave/themes/bootstrap.py
pweave/themes/cerulean.py
pweave/themes/journal.py
pweave/themes/skeleton.py
