Metadata-Version: 2.0
Name: Pweave
Version: 0.30.3
Summary: Scientific reports with embedded python computations with reST, LaTeX or markdown
Home-page: http://mpastell.com/pweave
Author: Matti Pastell
Author-email: matti.pastell@helsinki.fi
License: LICENSE.txt
Platform: UNKNOWN
Classifier: Development Status :: 5 - Production/Stable
Classifier: Topic :: Text Processing :: Markup
Classifier: Intended Audience :: Science/Research
Classifier: Topic :: Scientific/Engineering
Classifier: Topic :: Software Development :: Documentation
Classifier: Topic :: Documentation :: Sphinx
Classifier: License :: OSI Approved :: BSD License
Classifier: Programming Language :: Python :: 3 :: Only
Classifier: Programming Language :: Python :: 3.5
Classifier: Programming Language :: Python :: 3.6
Requires-Dist: markdown
Requires-Dist: pygments
Requires-Dist: ipython (>=6.0)
Requires-Dist: nbformat
Requires-Dist: nbconvert
Requires-Dist: jupyter-client
Requires-Dist: ipykernel
Provides-Extra: doc
Requires-Dist: sphinx; extra == 'doc'
Requires-Dist: sphinx-rtd-theme; extra == 'doc'
Provides-Extra: test
Requires-Dist: scipy; extra == 'test'
Requires-Dist: matplotlib; extra == 'test'
Requires-Dist: coverage; extra == 'test'
Requires-Dist: ipython; extra == 'test'
Requires-Dist: nose; extra == 'test'
Requires-Dist: notebook; extra == 'test'
